{
  "name": "MechWarrior 5: Mercenaries",
  "game_id": "MechWarrior_5__Mercenaries",
  "version": 1,
  "exe_name": "MW5Mercs/Binaries/Win64/MechWarrior-Win64-Shipping.exe",
  "deploy_type": "standard",
  "mod_data_path": "MW5Mercs/Mods",
  "steam_id": "784080",
  "nexus_game_domain": "mechwarrior5mercenaries",
  "editable": false,
  "image_url": "https://cdn2.steamgriddb.com/icon/0a8ddaad1c78d73b557663e728653f32/32/256x256.png",
  "mod_folder_strip_prefixes": [],
  "conflict_ignore_filenames": [],
  "mod_folder_strip_prefixes_post": [],
  "mod_install_prefix": "",
  "mod_required_top_level_folders": [],
  "mod_auto_strip_until_required": false,
  "mod_required_file_types": [],
  "mod_install_as_is_if_no_match": false,
  "restore_before_deploy": true,
  "normalize_folder_case": true,
  "wine_dll_overrides": {},
  "custom_routing_rules": [],
  "custom_frameworks": {}
}
